space_bandits/__init__.py
space_bandits/bandit_algorithm.py
space_bandits/bayesian_nn.py
space_bandits/contextual_dataset.py
space_bandits/linear.py
space_bandits/neural_bandit_model.py
space_bandits/neural_linear.py
space_bandits/toy_problem.py
space_bandits-0.0.993.dist-info/LICENSE
space_bandits-0.0.993.dist-info/METADATA
space_bandits-0.0.993.dist-info/WHEEL
space_bandits-0.0.993.dist-info/top_level.txt
space_bandits-0.0.993.dist-info/RECORD
