Metadata-Version: 2.1
Name: space-bandits
Version: 0.0.993
Summary: Deep Bayesian Contextual Bandits Library
Home-page: https://github.com/fellowship/space-bandits
Author: Michael Klear
Author-email: michael@fellowship.ai
License: UNKNOWN
Download-URL: https://github.com/fellowship/space-bandits/archive/v0.0.993.tar.gz
Platform: UNKNOWN
License-File: LICENSE
Requires-Dist: torch
Requires-Dist: numpy
Requires-Dist: scipy
Requires-Dist: pandas
Requires-Dist: cython
Requires-Dist: scikit-learn
